adafruit_ina3221.py
adafruit_circuitpython_ina3221-1.2.1.dist-info/licenses/LICENSE
adafruit_circuitpython_ina3221-1.2.1.dist-info/METADATA
adafruit_circuitpython_ina3221-1.2.1.dist-info/WHEEL
adafruit_circuitpython_ina3221-1.2.1.dist-info/top_level.txt
adafruit_circuitpython_ina3221-1.2.1.dist-info/RECORD
