Metadata-Version: 2.4
Name: adafruit-circuitpython-ina3221
Version: 1.2.1
Summary: CircuitPython driver for the INA3221 Triple 0-26 VDC, ±3.2 Amp Power Monitor
Author-email: Adafruit Industries <circuitpython@adafruit.com>
License: MIT
Project-URL: Homepage, https://github.com/adafruit/Adafruit_CircuitPython_INA3221
Keywords: adafruit,blinka,circuitpython,micropython,ina3221,power,monitor,,i2c
Classifier: Intended Audience :: Developers
Classifier: Topic :: Software Development :: Libraries
Classifier: Topic :: Software Development :: Embedded Systems
Classifier: Topic :: System :: Hardware
Classifier: License :: OSI Approved :: MIT License
Classifier: Programming Language :: Python :: 3
License-File: LICENSE
Requires-Dist: Adafruit-Blinka
Requires-Dist: adafruit-circuitpython-busdevice
Provides-Extra: optional
Dynamic: license-file
